hfoGUI/__init__.py
hfoGUI/__main__.py
hfoGUI/main.py
hfoGUI/core/ChooseFile.py
hfoGUI/core/GUI_Utils.py
hfoGUI/core/GraphSettings.py
hfoGUI/core/Score.py
hfoGUI/core/TFA_Functions.py
hfoGUI/core/TFplots.py
hfoGUI/core/Tint_Matlab.py
hfoGUI/core/__init__.py
hfoGUI/core/defaultParameters.py
hfoGUI/core/filtering.py
hfoGUI/exporters/Exporter.py
hfoGUI/exporters/ImageExporter.py
hfoGUI/exporters/__init__.py
hfoGUI/exporters/tests/__init__.py
hfoGUI/exporters/tests/test_csv.py
hfoGUI/exporters/tests/test_svg.py
hfoGUI/img/GEBA_Logo.png
hfoGUI/img/__init__.py
hfoGUI-1.0.10.dist-info/LICENSE
hfoGUI-1.0.10.dist-info/METADATA
hfoGUI-1.0.10.dist-info/WHEEL
hfoGUI-1.0.10.dist-info/top_level.txt
hfoGUI-1.0.10.dist-info/RECORD
