Metadata-Version: 2.1
Name: hfoGUI
Version: 1.0.10
Summary: hfoGUI - a data visualization GUI for TINT data.
Home-page: https://github.com/HussainiLab/hfoGUI.git
Author: Geoffrey Barrett
Author-email: geoffrey.m.barrett@gmail.com
License: UNKNOWN
Platform: UNKNOWN
Classifier: Programming Language :: Python :: 3.7 
Classifier: License :: OSI Approved :: GNU General Public License v3 (GPLv3) 
Classifier: Operating System :: OS Independent
Requires-Dist: PyQt5
Requires-Dist: pillow
Requires-Dist: numpy
Requires-Dist: PyQtGraph
Requires-Dist: scipy
Requires-Dist: matplotlib
Requires-Dist: pandas
Requires-Dist: pyfftw
